print_columns-1.0.0.dist-info/METADATA
print_columns-1.0.0.dist-info/WHEEL
print_columns/__init__.py
print_columns-1.0.0.dist-info/RECORD
