Metadata-Version: 2.1
Name: print_columns
Version: 1.0.0
Summary: A simple package for printing text to the terminal in columns
Author-Email: Matt Zhang <set.stun@gmail.com>
License: MIT
Project-URL: Homepage, https://github.com/MattUnderscoreZhang/print_columns
Requires-Python: >=3.8
Requires-Dist: termcolor>=2.3.0
Requires-Dist: build>=1.0.3
